parxy_core/__init__.py
parxy_core/drivers/__init__.py
parxy_core/drivers/abstract_driver.py
parxy_core/drivers/factory.py
parxy_core/drivers/llamaparse.py
parxy_core/drivers/llmwhisperer.py
parxy_core/drivers/pdfact.py
parxy_core/drivers/pymupdf.py
parxy_core/drivers/unstructured_local.py
parxy_core/exceptions/__init__.py
parxy_core/exceptions/authentication_exception.py
parxy_core/exceptions/file_not_found_exception.py
parxy_core/exceptions/parsing_exception.py
parxy_core/exceptions/unsupported_format_exception.py
parxy_core/facade/__init__.py
parxy_core/facade/parxy.py
parxy_core/models/__init__.py
parxy_core/models/config.py
parxy_core/models/models.py
parxy_core/py.typed
parxy_core/tracing/__init__.py
parxy_core/tracing/tracer.py
parxy_cli/.env.example
parxy_cli/__init__.py
parxy_cli/cli.py
parxy_cli/compose.example.yaml
parxy-0.1.0.dist-info/WHEEL
parxy-0.1.0.dist-info/entry_points.txt
parxy-0.1.0.dist-info/METADATA
parxy-0.1.0.dist-info/RECORD
