Metadata-Version: 2.3
Name: parxy
Version: 0.1.0
Summary: Parxy document processing gateway
Author: Alessio Vertemati
Author-email: Alessio Vertemati <alessio@oneofftech.xyz>
Requires-Dist: pydantic>=2.11.7
Requires-Dist: pydantic-settings>=2.10.1
Requires-Dist: pymupdf>=1.26.3
Requires-Dist: requests>=2.32.4
Requires-Dist: validators>=0.35.0
Requires-Dist: typer>=0.9.0
Requires-Dist: rich>=13.7.0
Requires-Dist: python-dotenv>=1.0.1
Requires-Dist: importlib-resources>=6.1.3
Requires-Dist: llama-cloud-services>=0.6.60 ; extra == 'all'
Requires-Dist: llmwhisperer-client>=2.4.2 ; extra == 'all'
Requires-Dist: unstructured[pdf]>=0.18.13 ; extra == 'all'
Requires-Dist: llama-cloud-services>=0.6.60 ; extra == 'llama'
Requires-Dist: llmwhisperer-client>=2.4.2 ; extra == 'llmwhisperer'
Requires-Dist: unstructured[pdf]>=0.18.13 ; extra == 'unstructured-local'
Requires-Python: >=3.12
Provides-Extra: all
Provides-Extra: llama
Provides-Extra: llmwhisperer
Provides-Extra: unstructured-local
